eif.py
version.py
eif-1.0.2.dist-info/METADATA
eif-1.0.2.dist-info/RECORD
eif-1.0.2.dist-info/WHEEL
eif-1.0.2.dist-info/top_level.txt
