Metadata-Version: 2.1
Name: eif
Version: 1.0.2
Summary: Extended Isolation Forest for anomaly detection
Home-page: https://github.com/sahandha/eif
Author: Matias Carrasco Kind , Sahand Hariri
Author-email: mcarras2@illinois.edu , sahandha@gmail.com
License: License.txt
Platform: UNKNOWN
Requires-Dist: numpy
